Debug_Interface.v
// Author: Ha How Ung
// Written on: 18 April 2021 (Mon)
// Title: Debug Interface

module Debug_Interface (
	input [3:0] Ain, Bin, ALUout,
	input [2:0] ALUop,
	input [1:0] dsel,
	output reg [7:0] dout
);

	always@(dsel, Ain, Bin, ALUout, ALUop)
		case(dsel)
			2'b00: dout = {4'b0000, Ain};
			2'b01: dout = {4'b0000, Bin};
			2'b10: dout = {4'b0000, ALUout};
			default: dout = {5'b00000, ALUop};
		endcase

endmodule

bcd7segDEC.v
// Author: Ha How Ung
// Written on: 18 April 2022 (Mon)
// Title: BCD to 7seg decoder

module bcd7segDEC (
	input [3:0] SW, // represent 4-bit binary number (BCD) as input

	output reg [7:0] HEX5,
	output reg [9:0] LEDR
);
	
	// Hexadecimal numbers on 7-segment LED display
	parameter zero=8'b0011_1111, one=8'b0000_0110, two=8'b0101_1011, three=8'b0100_1111, four=8'b0110_0110,
					five=8'b0110_1101, six=8'b0111_1101, seven=8'b0000_0111, eight=8'b0111_1111, nine=8'b0110_1111;
	
	always@(SW)
	begin
	
		LEDR = SW;

		case(SW)
			// For DE10-Lite board - HEX LEDs are active low & in reversed order
			0: HEX5 = ~zero;
			1:	HEX5 = ~one;
			2: HEX5 = ~two;
			3:	HEX5 = ~three;
			4: HEX5 = ~four;
			5: HEX5 = ~five;
			6: HEX5 = ~six;
			7: HEX5 = ~seven;
			8: HEX5 = ~eight;
			9: HEX5 = ~nine;
			default: HEX5 = ~8'b1000_0000;
		endcase
	end
endmodule

ALU.v
// Author: Ha How Ung
// Written on: 8 April 2021 (Fri)
// Title: Arithmetic Logic Unit

module ALU (
	input [3:0] Ain, Bin,
	input [2:0] ALUop,
	output reg [3:0] ALUout
);

	always@(ALUop, Ain, Bin)
		case(ALUop)
			3'b000: ALUout = Ain;
			3'b001: ALUout = Ain | Bin;
			3'b010: ALUout = Ain ^ Bin;
			3'b011: ALUout = Ain & Bin;
			3'b100: ALUout = Ain - Bin;
			3'b101: ALUout = Ain + Bin;
			default: ALUout = Bin;
		endcase

endmodule

DPU.v
// Author: Ha How Ung
// Written on: 18 April 2022 (Mon)
// Title: Datapath Unit (DPU)

module DPU (
	input [15:0] din,
	input [1:0] dsel,
	output [7:0] seg, dout
);

	wire [3:0] Ain = din[3:0];
	wire [3:0] Bin = din[7:4];
	wire [2:0] ALUop = din[10:8];
	wire [3:0] ALUout;

	
	ALU u0 (.Ain(Ain), .Bin(Bin), .ALUop(ALUop), .ALUout(ALUout));
	bcd7segDEC u1 (.SW(ALUout), .HEX5(seg), .LEDR());
	Debug_Interface u2 (.ALUout(ALUout), .Ain(Ain), .Bin(Bin), .ALUop(ALUop), .dsel(dsel), .dout(dout));

endmodule

DPU_testbench.v
// Author: Ha How Ung
// Written on: 18 April 2022 (Mon)
// Title: Testbench - Datapath Unit (DPU)

`timescale 10ns/1ns

module DPU_testbench();
  
  reg [15:0] din;
  reg [1:0] dsel;
  wire [7:0] seg, dout;
  
  DPU DUT (.din(din), .dsel(dsel), .seg(seg), .dout(dout));
  
  initial
  begin
    $monitor($time, " din=%d, dsel=%b, seg=%b, dout=%d", din,dsel,seg,dout);
  end
  
  integer stepSize = 100;
  
  initial
  begin
    $dumpfile("DPU.vcd");
    $dumpvars(1, DPU_testbench);
    
    #0 din=0; dsel=0;
    
    repeat (1023 / stepSize)
    begin
      #50 din <= din + stepSize; dsel <= 0;
      repeat (3)
      begin
      	#50 dsel <= dsel + 1;
      end
    end
    
  end
  
endmodule

DPU.vcd
$date
	Tue Apr 19 00:42:54 2022
$end
$version
	Icarus Verilog
$end
$timescale
	1ns
$end
$scope module DPU_testbench $end
$var wire 8 ! seg [7:0] $end
$var wire 8 " dout [7:0] $end
$var reg 16 # din [15:0] $end
$var reg 2 $ dsel [1:0] $end
$var integer 32 % stepSize [31:0] $end
$upscope $end
$enddefinitions $end
#0
$dumpvars
b1100100 %
b0 $
b0 #
b0 "
b11000000 !
$end
#500
b10011001 !
b100 "
b1100100 #
#1000
b110 "
b1 $
#1500
b100 "
b10 $
#2000
b0 "
b11 $
#2500
b10000000 !
b1000 "
b0 $
b11001000 #
#3000
b1100 "
b1 $
#3500
b1000 "
b10 $
#4000
b0 "
b11 $
#4500
b1111111 !
b1100 "
b0 $
b100101100 #
#5000
b10 "
b1 $
#5500
b1110 "
b10 $
#6000
b1 "
b11 $
#6500
b10010000 !
b0 "
b0 $
b110010000 #
#7000
b1001 "
b1 $
#7500
b10 $
#8000
b1 "
b11 $
#8500
b1111111 !
b100 "
b0 $
b111110100 #
#9000
b1111 "
b1 $
#9500
b10 $
#10000
b1 "
b11 $
#10500
b1000 "
b0 $
b1001011000 #
#11000
b101 "
b1 $
#11500
b1101 "
b10 $
#12000
b10 "
b11 $
#12500
b11111000 !
b1100 "
b0 $
b1010111100 #
#13000
b1011 "
b1 $
#13500
b111 "
b10 $
#14000
b10 "
b11 $
#14500
b11000000 !
b0 "
b0 $
b1100100000 #
#15000
b10 "
b1 $
#15500
b0 "
b10 $
#16000
b11 "
b11 $
#16500
b100 "
b0 $
b1110000100 #
#17000
b1000 "
b1 $
#17500
b0 "
b10 $
#18000
b11 "
b11 $
#18500
b10000000 !
b1000 "
b0 $
b1111101000 #
#19000
b1110 "
b1 $
#19500
b1000 "
b10 $
#20000
b11 "
b11 $
